README.rst
setup.cfg
setup.py
healthcheck/__init__.py
healthcheck/environmentdump.py
healthcheck/healthcheck.py
healthcheck/security.py
healthcheck/timeout.py
healthcheck/tornado_handler.py
py_healthcheck.egg-info/PKG-INFO
py_healthcheck.egg-info/SOURCES.txt
py_healthcheck.egg-info/dependency_links.txt
py_healthcheck.egg-info/not-zip-safe
py_healthcheck.egg-info/requires.txt
py_healthcheck.egg-info/top_level.txt