Metadata-Version: 1.1
Name: py-healthcheck
Version: 1.10.0
Summary: Adds healthcheck endpoints to Flask or Tornado apps
Home-page: https://github.com/ateliedocodigo/py-healthcheck
Author: Luis Fernando Gomes
Author-email: luiscoms@ateliedocodigo.com.br
License: MIT
Download-URL: https://github.com/ateliedocodigo/py-healthcheck/tarball/1.10.0
Platform: any
Classifier: Development Status :: 5 - Production/Stable
Classifier: Environment :: Web Environment
Classifier: Framework :: Flask
Classifier: Programming Language :: Python :: 2.7
Classifier: Programming Language :: Python :: 3
